{"ranking":[{"name":"Argentina","value":186229},{"name":"Australia","value":394179},{"name":"Belgium","value":322445},{"name":"Canada","value":403702},{"name":"China","value":341150},{"name":"France","value":533857},{"name":"Germany","value":620706},{"name":"India","value":253532},{"name":"Indonesia","value":375797},{"name":"Japan","value":502418},{"name":"Mexico","value":165157},{"name":"Poland","value":341674},{"name":"Russia","value":218777},{"name":"Singapore","value":200929},{"name":"South Korea","value":290097},{"name":"Ukraine","value":196697},{"name":"United Kingdom","value":426444},{"name":"United States of America","value":378538},{"name":"Vietnam","value":213655}]}
