{"ranking":[{"name":"Argentina","value":183824},{"name":"Australia","value":384721},{"name":"Belgium","value":322279},{"name":"Canada","value":399909},{"name":"China","value":338979},{"name":"France","value":527094},{"name":"Germany","value":615720},{"name":"India","value":249603},{"name":"Indonesia","value":372134},{"name":"Japan","value":494899},{"name":"Mexico","value":163686},{"name":"Poland","value":334478},{"name":"Russia","value":220497},{"name":"Singapore","value":198491},{"name":"South Korea","value":288705},{"name":"Ukraine","value":193463},{"name":"United Kingdom","value":425312},{"name":"United States of America","value":375120},{"name":"Vietnam","value":212940}]}
