{"ranking":[{"name":"Argentina","value":186854},{"name":"Australia","value":373741},{"name":"Belgium","value":317545},{"name":"Canada","value":388206},{"name":"China","value":339732},{"name":"France","value":523920},{"name":"Germany","value":608269},{"name":"India","value":262722},{"name":"Indonesia","value":395711},{"name":"Japan","value":486901},{"name":"Mexico","value":148370},{"name":"Poland","value":334642},{"name":"Russia","value":213575},{"name":"Singapore","value":210026},{"name":"South Korea","value":279205},{"name":"Ukraine","value":192217},{"name":"United Kingdom","value":435357},{"name":"United States of America","value":389390},{"name":"Vietnam","value":206174}]}
