{"ranking":[{"name":"Argentina","value":193747},{"name":"Australia","value":390663},{"name":"Belgium","value":319755},{"name":"Canada","value":390018},{"name":"China","value":343601},{"name":"France","value":532417},{"name":"Germany","value":613829},{"name":"India","value":258228},{"name":"Indonesia","value":407846},{"name":"Japan","value":504569},{"name":"Mexico","value":156422},{"name":"Poland","value":342543},{"name":"Russia","value":216050},{"name":"Singapore","value":211904},{"name":"South Korea","value":285377},{"name":"Ukraine","value":193334},{"name":"United Kingdom","value":433010},{"name":"United States of America","value":381501},{"name":"Vietnam","value":209106}]}
