{"ranking":[{"name":"Argentina","value":188289},{"name":"Australia","value":376078},{"name":"Belgium","value":327095},{"name":"Canada","value":389567},{"name":"China","value":338088},{"name":"France","value":535576},{"name":"Germany","value":605953},{"name":"India","value":257794},{"name":"Indonesia","value":393954},{"name":"Japan","value":498438},{"name":"Mexico","value":129963},{"name":"Poland","value":346376},{"name":"Russia","value":214858},{"name":"Singapore","value":214259},{"name":"South Korea","value":275926},{"name":"Ukraine","value":194012},{"name":"United Kingdom","value":437896},{"name":"United States of America","value":395523},{"name":"Vietnam","value":209624}]}
