{"ranking":[{"name":"Argentina","value":183785},{"name":"Australia","value":383745},{"name":"Belgium","value":321724},{"name":"Canada","value":399256},{"name":"China","value":337787},{"name":"France","value":525870},{"name":"Germany","value":614655},{"name":"India","value":246730},{"name":"Indonesia","value":369786},{"name":"Japan","value":494986},{"name":"Mexico","value":163365},{"name":"Poland","value":333625},{"name":"Russia","value":219718},{"name":"Singapore","value":197886},{"name":"South Korea","value":291456},{"name":"Ukraine","value":193062},{"name":"United Kingdom","value":424794},{"name":"United States of America","value":375120},{"name":"Vietnam","value":212289}]}
